discrete_math/__init__.py
discrete_math/cli.py
discrete_math/combinatorics.py
discrete_math/functions.py
discrete_math/graphs.py
discrete_math/logic.py
discrete_math/number_theory.py
discrete_math/relations.py
discrete_math/sets.py
discrete_math_toolkit-0.2.0.dist-info/licenses/LICENSE
discrete_math_toolkit-0.2.0.dist-info/METADATA
discrete_math_toolkit-0.2.0.dist-info/WHEEL
discrete_math_toolkit-0.2.0.dist-info/entry_points.txt
discrete_math_toolkit-0.2.0.dist-info/top_level.txt
discrete_math_toolkit-0.2.0.dist-info/RECORD
