Metadata-Version: 2.4
Name: discrete-math-toolkit
Version: 0.2.0
Summary: A comprehensive Python package for discrete mathematics automation
Author-email: CodewithTanzeel <ahmedtanzeel681@gmail.com>
License: MIT
Project-URL: Homepage, https://github.com/CodewithTanzeel/pypi-package-dm
Project-URL: Documentation, https://github.com/CodewithTanzeel/pypi-package-dm#readme
Project-URL: Repository, https://github.com/CodewithTanzeel/pypi-package-dm
Project-URL: Issues, https://github.com/CodewithTanzeel/pypi-package-dm/issues
Keywords: discrete-mathematics,graph-theory,combinatorics,logic,set-theory,number-theory,relations,mathematics,education
Classifier: Development Status :: 3 - Alpha
Classifier: Intended Audience :: Education
Classifier: Intended Audience :: Science/Research
Classifier: Topic :: Scientific/Engineering :: Mathematics
Classifier: Topic :: Education
Classifier: License :: OSI Approved :: MIT License
Classifier: Programming Language :: Python :: 3
Classifier: Programming Language :: Python :: 3.8
Classifier: Programming Language :: Python :: 3.9
Classifier: Programming Language :: Python :: 3.10
Classifier: Programming Language :: Python :: 3.11
Classifier: Programming Language :: Python :: 3.12
Classifier: Operating System :: OS Independent
Requires-Python: >=3.8
License-File: LICENSE
Requires-Dist: numpy>=1.20.0
Requires-Dist: matplotlib>=3.3.0
Requires-Dist: networkx>=2.5
Requires-Dist: sympy>=1.8
Provides-Extra: dev
Requires-Dist: pytest>=7.0; extra == "dev"
Requires-Dist: pytest-cov>=3.0; extra == "dev"
Requires-Dist: black>=22.0; extra == "dev"
Requires-Dist: flake8>=4.0; extra == "dev"
Requires-Dist: mypy>=0.950; extra == "dev"
Requires-Dist: sphinx>=4.0; extra == "dev"
Requires-Dist: build>=0.7; extra == "dev"
Requires-Dist: twine>=4.0; extra == "dev"
Dynamic: license-file
